cubicweb_celery/__init__.py
cubicweb_celery/__pkginfo__.py
cubicweb_celery/sobjects.py
cubicweb_celery/migration/ddl.sql
cubicweb_celery/migration/postcreate.py
cubicweb_celery/migration/table.sql
cubicweb_celery-1.1.1.dist-info/METADATA
cubicweb_celery-1.1.1.dist-info/WHEEL
cubicweb_celery-1.1.1.dist-info/entry_points.txt
cubicweb_celery-1.1.1.dist-info/top_level.txt
cubicweb_celery-1.1.1.dist-info/RECORD
