Metadata-Version: 2.1
Name: cubicweb-celery
Version: 1.1.1
Summary: Celery cube
Home-page: https://forge.extranet.logilab.fr/cubicweb/cubes/celery
Author: Logilab
Author-email: contact@logilab.fr
License: LGPL
Classifier: Environment :: Web Environment
Classifier: Framework :: CubicWeb
Classifier: Programming Language :: Python
Classifier: Programming Language :: Python :: 3
Classifier: Programming Language :: Python :: 3 :: Only
Classifier: Programming Language :: JavaScript
Requires-Python: >=3.9.2
Requires-Dist: celery~=5.0
Requires-Dist: cubicweb<5.0.0,>=3.38.16
